pulpcore/__init__.py
pulpcore/client/__init__.py
pulpcore/client/pulp_deb/__init__.py
pulpcore/client/pulp_deb/api_client.py
pulpcore/client/pulp_deb/api_response.py
pulpcore/client/pulp_deb/configuration.py
pulpcore/client/pulp_deb/exceptions.py
pulpcore/client/pulp_deb/py.typed
pulpcore/client/pulp_deb/rest.py
pulpcore/client/pulp_deb/api/__init__.py
pulpcore/client/pulp_deb/api/acs_deb_api.py
pulpcore/client/pulp_deb/api/content_generic_contents_api.py
pulpcore/client/pulp_deb/api/content_installer_file_indices_api.py
pulpcore/client/pulp_deb/api/content_installer_packages_api.py
pulpcore/client/pulp_deb/api/content_package_indices_api.py
pulpcore/client/pulp_deb/api/content_package_release_components_api.py
pulpcore/client/pulp_deb/api/content_packages_api.py
pulpcore/client/pulp_deb/api/content_release_architectures_api.py
pulpcore/client/pulp_deb/api/content_release_components_api.py
pulpcore/client/pulp_deb/api/content_release_files_api.py
pulpcore/client/pulp_deb/api/content_releases_api.py
pulpcore/client/pulp_deb/api/content_source_indices_api.py
pulpcore/client/pulp_deb/api/content_source_packages_api.py
pulpcore/client/pulp_deb/api/content_source_release_components_api.py
pulpcore/client/pulp_deb/api/deb_copy_api.py
pulpcore/client/pulp_deb/api/distributions_apt_api.py
pulpcore/client/pulp_deb/api/publications_apt_api.py
pulpcore/client/pulp_deb/api/publications_verbatim_api.py
pulpcore/client/pulp_deb/api/remotes_apt_api.py
pulpcore/client/pulp_deb/api/repositories_apt_api.py
pulpcore/client/pulp_deb/api/repositories_apt_versions_api.py
pulpcore/client/pulp_deb/models/__init__.py
pulpcore/client/pulp_deb/models/apt_repository_sync_url.py
pulpcore/client/pulp_deb/models/async_operation_response.py
pulpcore/client/pulp_deb/models/content_summary_response.py
pulpcore/client/pulp_deb/models/copy.py
pulpcore/client/pulp_deb/models/deb_apt_alternate_content_source.py
pulpcore/client/pulp_deb/models/deb_apt_alternate_content_source_response.py
pulp_deb_client-3.8.1.dist-info/METADATA
pulp_deb_client-3.8.1.dist-info/WHEEL
pulp_deb_client-3.8.1.dist-info/top_level.txt
pulp_deb_client-3.8.1.dist-info/RECORD
